fast_sva/ch8/noclksok.sv
module  top2;
  bit  clk_gated, clk_ref, en=1, en1=1;
  int pass, pass2, err, err2, tbcount;
  always #1 clk_ref=!clk_ref; 
  always_comb clk_gated = clk_ref && en1;
  always en1 = #4 en;
    // When the en signal is pulled low, the clk_gated can still jump normally for
    // a maximum of 3 times, and then it must be turned off, 
    // that is, it should remain unchanged.
    task automatic t_clk_en0();
       int count; 
       fork
        #10; // 5 clk_gateds, modify as needed
         forever @(posedge clk_gated) if(!en) begin 
            count=count+1;
            tbcount=count; // debbug
         end 
       join_any
      am_3clk_after_en: assert(count <= 3) pass2++; else err2=err2+1;
    endtask
    // fire the task 
    // cover property(@(posedge clk_ref) !en |-> (1, t_clk_en0()));
    always @(negedge(en)) t_clk_en0(); 

    // Using the tb clock 
    property p_noclk_en; // adjust the max count allowed 
      int count=0; 
      @(posedge clk_ref) $fell(en) |-> ##1 
         ((1, count=count+clk_gated)[*1:$]  intersect  $rose(en)[->1]) ##0 count<=3 ;
    endproperty
    ap_noclk_en: assert property(p_noclk_en) pass++; else err=err+1; 

    
    initial begin 
      $dumpfile("dump.vcd"); $dumpvars;      
      en1=1;en=1;
      repeat(5) @(posedge clk_ref);
      en<=0;
      repeat(15) @(posedge clk_ref);
      en<=1;  
      repeat(15) @(posedge clk_ref);
      #30; $finish();
    end
endmodule

fast_sva/ch8/dump.vcd
$date
	Mon Feb 24 17:18:49 2025
$end
$version
	QuestaSim Version 2024.3_2
$end
$timescale
	1ns
$end

$scope module top2 $end
$var reg 1 ! clk_gated $end
$var reg 1 " clk_ref $end
$var reg 1 # en $end
$var reg 1 $ en1 $end
$var integer 32 % pass $end
$var integer 32 & pass2 $end
$var integer 32 ' err $end
$var integer 32 ( err2 $end
$var integer 32 ) tbcount $end

$scope task t_clk_en0 $end

$scope begin am_3clk_after_en $end
$upscope $end
$upscope $end

$scope begin ap_noclk_en $end
$upscope $end
$upscope $end

$scope begin std $end
$upscope $end
$enddefinitions $end
#0
$dumpvars
0!
0"
1#
1$
b0 %
b0 &
b0 '
b0 (
b0 )
$end
#1
1"
1!
#2
0"
0!
#3
1"
1!
#4
0"
0!
#5
1"
1!
#6
0"
0!
#7
1"
1!
#8
0"
0!
#9
1"
1!
0#
#10
0"
0!
#11
1"
1!
b1 )
#12
0"
0!
#13
1"
1!
b10 )
#14
0"
0!
#15
1"
1!
b11 )
#16
0$
0"
0!
#17
1"
#18
0"
#19
b1 &
1"
#20
0"
#21
1"
#22
0"
#23
1"
#24
0"
#25
1"
#26
0"
#27
1"
#28
0"
#29
1"
#30
0"
#31
1"
#32
0"
#33
1"
#34
0"
#35
1"
#36
0"
#37
1"
#38
0"
#39
1"
1#
#40
0"
#41
1"
b1 %
#42
0"
#43
1"
#44
1$
0"
